python_module/__init__.py
python_module/_logger.py
python_module/dependency_injector.py
python_module/inject.py
python_module/injector_instance.py
python_module/module.py
python_module/typing/__init__.py
python_module/typing/module_type.py
secondary_module/__init__.py
secondary_module/second_module.py
secondary_module/services/__init__.py
secondary_module/services/provider.py
secondary_module/services/service.py
secondary_module/services/service_base.py
tests/__init__.py
tests/tests_core.py
py_module_injector-0.1.3.dist-info/METADATA
py_module_injector-0.1.3.dist-info/WHEEL
py_module_injector-0.1.3.dist-info/entry_points.txt
py_module_injector-0.1.3.dist-info/top_level.txt
py_module_injector-0.1.3.dist-info/RECORD
