Metadata-Version: 2.2
Name: py-module-injector
Version: 0.1.3
Summary: Uma biblioteca de modularização em python
Author: Cleverson Pedroso
Author-email: cleverson212121@gmail.com
Requires-Dist: typing-extensions
Dynamic: author
Dynamic: author-email
Dynamic: description
Dynamic: description-content-type
Dynamic: requires-dist
Dynamic: summary
